pyconfluence
