Metadata-Version: 1.1
Name: pyconfluence
Version: 1.1.3
Summary: An API wrapper for Atlassian Confluence
Home-page: https://github.com/FulcrumIT/pyconfluence
Author: Caleb Hawkins
Author-email: hawkins.caleb93@gmail.com
License: UNKNOWN
Download-URL: https://github.com/FulcrumIT/pyconfluence/tarball/1.1.3
Keywords: confluence
Platform: UNKNOWN
